bvtools/argtools.py
bvtools/enum.py
bvtools/functoolz.py
bvtools/itertoolz.py
bvtools/misc.py
bvtools/pdf.py
bvtools/polars.py
bvtools-0.1.5.dist-info/METADATA
bvtools-0.1.5.dist-info/WHEEL
bvtools-0.1.5.dist-info/RECORD
