Metadata-Version: 2.1
Name: bvtools
Version: 0.1.5
Summary: A collection of tools
License: MIT
Author: Torstein Sørnes
Author-email: t.soernes@gmail.com
Requires-Python: >=3.11,<4.0
Classifier: License :: OSI Approved :: MIT License
Classifier: Programming Language :: Python :: 3
Classifier: Programming Language :: Python :: 3.11
Classifier: Programming Language :: Python :: 3.12
Classifier: Programming Language :: Python :: 3.13
Requires-Dist: betterpathlib (>=0.1.4,<0.2.0)
